{"cameraMode":{"drawMode":0,"name":"Shaded","section":"Shading Mode"},"sceneLighting":true,"audioPlay":false,"sceneViewState":{"m_AlwaysRefresh":false,"showFog":true,"showSkybox":true,"showFlares":true,"showImageEffects":true,"showParticleSystems":true,"showVisualEffectGraphs":true,"m_FxEnabled":true},"in2DMode":false,"pivot":{"x":8.006369590759278,"y":1.2562446594238282,"z":17.07229232788086},"rotation":{"x":0.008140642195940018,"y":-0.3535868525505066,"z":-0.0030436189845204355,"w":-0.9354436993598938},"size":8.383674621582032,"orthographic":false}